robotframeworkinteractive/Main.robot
robotframeworkinteractive/__init__.py
robotframeworkinteractive/__main__.py
robotframeworkinteractive/robotframeworkinteractive.py
robotframeworkinteractive-1.0.5.dist-info/LICENSE
robotframeworkinteractive-1.0.5.dist-info/METADATA
robotframeworkinteractive-1.0.5.dist-info/WHEEL
robotframeworkinteractive-1.0.5.dist-info/entry_points.txt
robotframeworkinteractive-1.0.5.dist-info/top_level.txt
robotframeworkinteractive-1.0.5.dist-info/RECORD
