Metadata-Version: 2.1
Name: robotframeworkinteractive
Version: 1.0.5
Summary: Run Robot Framework interactively from the command line
Home-page: https://github.com/tylerjosephrose/robotframework-interactive
Author: Tyler Rose
Author-email: tylerjosephrose@gmail.com
License: MIT
Classifier: Development Status :: 5 - Production/Stable
Classifier: License :: OSI Approved :: MIT License
Classifier: Framework :: Robot Framework :: Tool
Classifier: Operating System :: Microsoft :: Windows :: Windows 10
Classifier: Operating System :: POSIX
Classifier: Programming Language :: Python :: 3
Requires-Python: >=3.8
License-File: LICENSE
Requires-Dist: robotframework (>=3.2)
Requires-Dist: pyreadline
